{
  "paper_id": "ACL_2017_130",
  "title": "Enriching Complex Networks with Word Embeddings for Detecting Mild Cognitive Impairment from Speech Transcripts",
  "conference": "ACL",
  "domain": {
    "research_object": "通过分析患者的语音转录文本，检测轻度认知障碍（MCI）的方法。",
    "core_technique": "将词嵌入技术与复杂网络分析结合，提升对语音文本的认知障碍检测能力。",
    "application": "用于辅助医疗领域，通过自动化分析语音文本，早期筛查认知障碍患者。",
    "domains": [
      "自然语言处理",
      "医疗健康信息学"
    ]
  },
  "ideal": {
    "core_idea": "结合复杂网络与词嵌入分析语言特征检测轻度认知障碍。",
    "tech_stack": [
      "复杂网络分析",
      "词嵌入",
      "语言特征提取"
    ],
    "input_type": "患者语音转录文本",
    "output_type": "轻度认知障碍检测结果"
  },
  "skeleton": {
    "problem_framing": "论文通过介绍轻度认知障碍（MCI）对多种认知领域的影响，强调其作为阿尔茨海默病前临床阶段的重要性。通过突出记忆受损型MCI的高转化率，论证早期诊断和干预的必要性，并指出语言作为认知评估的重要信息源，为后续研究奠定基础。",
    "gap_pattern": "作者通过回顾相关文献，指出尽管已有研究关注语言变化与认知障碍的关系，但现有方法在自动化、客观量化语言特征方面仍有不足，尤其是在利用复杂网络理论分析语言数据以辅助早期诊断方面存在研究空白。",
    "method_story": "方法部分采用复杂网络理论，借助词共现模型对文本进行建模，并对模型做出针对邻近词语关系的微调。通过将每个单词视为节点，词间共现为边，形成无向图，突出方法的创新性和理论依据。",
    "experiments_story": "实验部分详细说明了使用Scikitlearn工具和多种分类器对不同数据集进行5折交叉验证，参数优化过程透明。通过对比多种特征表示方法（如复杂网络、词嵌入、词袋等），系统展示了模型效果，突出实验设计的全面性和严谨性。"
  },
  "tricks": [
    {
      "name": "定义和背景介绍",
      "type": "writing-level",
      "purpose": "为读者提供研究主题的背景信息，明确研究对象的临床意义",
      "location": "论文开头部分",
      "description": "通过对MCI和AD的定义、流行病学数据及早期诊断的重要性进行介绍，为后续研究方法和意义做铺垫。"
    },
    {
      "name": "引用前人研究支持论点",
      "type": "writing-level",
      "purpose": "增强论据可信度，体现研究基础",
      "location": "背景和方法论中多处",
      "description": "通过引用大量相关文献（如Teixeira et al., 2012; Muangpaisan et al., 2012等），展示研究与现有成果的关联和继承。"
    },
    {
      "name": "突出语言分析的应用前景",
      "type": "writing-level",
      "purpose": "强调研究创新性和实际价值，吸引读者关注",
      "location": "背景介绍后段",
      "description": "明确指出自动化语言分析对MCI早期诊断的潜力，并结合临床实际需求，突出研究意义。"
    },
    {
      "name": "综述现有检测方法",
      "type": "writing-level",
      "purpose": "展示领域内多种方法，凸显本研究方法的独特性",
      "location": "背景介绍后段",
      "description": "简单罗列机器学习、MRI、数据筛查等主流方法，为后续提出复杂网络方法做铺垫。"
    },
    {
      "name": "复杂网络理论引入",
      "type": "writing-level",
      "purpose": "为方法部分引入理论基础，说明方法选择理由",
      "location": "方法部分开头",
      "description": "介绍复杂网络在NLP任务中的应用，引用相关文献，说明该理论的适用性和前瞻性。"
    },
    {
      "name": "词共现模型（Word Adjacency Model）的选择与改进",
      "type": "method-level",
      "purpose": "构建文本网络模型以捕捉语言结构特征",
      "location": "方法部分",
      "description": "选择词共现模型，将文本中的每个词作为节点，相邻词之间建立边，并根据句法关系进行小幅调整。"
    },
    {
      "name": "网络的数学定义与形式化表达",
      "type": "method-level",
      "purpose": "确保方法的可复现性与严谨性",
      "location": "方法部分",
      "description": "用集合和邻接矩阵的方式，形式化定义网络的节点、边及其关系，便于后续特征提取和分析。"
    },
    {
      "name": "文本预处理流程的详细说明",
      "type": "method-level",
      "purpose": "消除噪声，提高模型有效性",
      "location": "方法部分",
      "description": "详细描述分词、去停用词和标点等预处理步骤，强调这些步骤对后续建模的影响。"
    },
    {
      "name": "对预处理步骤的有意识简化（不进行词形还原）",
      "type": "method-level",
      "purpose": "保留更多原始语言特征，适应研究数据特点",
      "location": "方法部分结尾",
      "description": "说明有意不进行lemmatization，并给出理由，体现对方法细节的思考和实验设计的合理性。"
    }
  ]
}